{
  "id": "obj-5",
  "slug": "kvartira-lida-yuzhnyy-gorodok-d-19",
  "title": "1-комнатная квартира в г. Лида в Южном Городке",
  "type": "Квартира",
  "dealType": "Продажа",
  "city": "Лида",
  "address": "Южный городок, д.19",
  "priceBYN": 108343,
  "priceUSD": 38500,
  "cardDescription": "1-комнатная квартира площадью 30,2 м² на 3 этаже 5-этажного дома 1981 года постройки. Жилая комната — 14,2 м², кухня — 6,7 м²",
  "rooms": 1,
  "roomsSeparate": null,
  "areaTotal": 30.2,
  "areaLiving": 14.2,
  "areaKitchen": 6.7,
  "areaSNB": null,
  "floor": 3,
  "floorsTotal": 5,
  "yearBuilt": 1981,
  "houseType": "Панельный",
  "layout": null,
  "recommended": true,
  "balcony": "Балкон",
  "renovation": "Отличный",
  "bathroom": "Совмещенный",
  "ownership": "Частная",
  "saleTerms": "Чистая продажа",
  "infrastructure": [],
  "location": {
    "lat": 53.8745,
    "lng": 25.3406
  },
  "additionalBuildings": [],
  "description": "Уютная 1-комнатная квартира с дизайнерским ремонтом в г. Лида, по адресу ул. Южный городок, 19. Квартира полностью готова к проживанию и не требует никаких дополнительных вложений. Отделка выполнена с использованием качественных современных материалов, интерьер продуман до мелочей и создаёт ощущение уюта и комфорта с первого шага. Общая площадь квартиры составляет 30,2 м², жилая — 14,2 м², кухня — 6,7 м². Квартира расположена на 3 этаже 5-этажного панельного дома 1981 года постройки, планировка удобная и функциональная, санузел совмещённый, имеется балкон. Состояние квартиры — отличное, аккуратное и ухоженное. Дом находится в тихом и спокойном районе с развитой инфраструктурой. В шаговой доступности расположены детский сад, школа, магазины, аптека и другие объекты повседневного спроса, что делает локацию особенно удобной для комфортной жизни",
  "features": [
    "Дизайнерский ремонт",
    "Можно заехать и жить сразу",
    "Качественные материалы",
    "Балкон",
    "Тихий район"
  ],
  "images": [
    "/images/objects/pic5-1.webp",
    "/images/objects/pic5-2.webp",
    "/images/objects/pic5-3.webp",
    "/images/objects/pic5-4.webp"
  ],
  "publishedAt": "2025-12-08",
  "contractNumber": "Договор № 64/4 от 08.12.2025",
  "livePriceBYN": 112578
}